pytorch_parquet_loader/__init__.py
pytorch_parquet_loader/dataloader.py
pytorch_parquet_loader/dataset.py
tests/__init__.py
tests/test_parquet_loader.py
pytorch_parquet_loader-0.1.1.dist-info/LICENSE
pytorch_parquet_loader-0.1.1.dist-info/METADATA
pytorch_parquet_loader-0.1.1.dist-info/WHEEL
pytorch_parquet_loader-0.1.1.dist-info/top_level.txt
pytorch_parquet_loader-0.1.1.dist-info/RECORD
