Metadata-Version: 2.1
Name: pytorch_parquet_loader
Version: 0.1.1
Summary: A library for loading large Parquet files as an IterableDataset in PyTorch using Dask.
Home-page: https://github.com/aditya6767/pytoch_parquet_loader
Author: Aditya Jaiswal
Author-email: aditya.jaiswal@gmail.com
Project-URL: PyPI, https://pypi.org/project/pytorch_parquet_loader/
Classifier: Programming Language :: Python :: 3
Classifier: License :: OSI Approved :: MIT License
Classifier: Operating System :: OS Independent
Requires-Python: >=3.9
License-File: LICENSE
Requires-Dist: torch==2.5.0
Requires-Dist: dask[complete]
Requires-Dist: pyarrow
Requires-Dist: pytest
Requires-Dist: fastparquet
Requires-Dist: setuptools
Requires-Dist: wheel
Requires-Dist: scikit-learn
